fastapi_mcp_openapi/__init__.py
fastapi_mcp_openapi/core.py
fastapi_mcp_openapi-0.1.4.dist-info/METADATA
fastapi_mcp_openapi-0.1.4.dist-info/WHEEL
fastapi_mcp_openapi-0.1.4.dist-info/licenses/LICENSE
fastapi_mcp_openapi-0.1.4.dist-info/RECORD
