Metadata-Version: 2.4
Name: fastapi-mcp-openapi
Version: 0.1.4
Summary: FastAPI MCP OpenAPI - A library that provides MCP tools for endpoint introspection in FastAPI applications
Author: Raquib Ul Alam (Kanak)
License-Expression: MIT
License-File: LICENSE
Keywords: api-documentation,fastapi,mcp,model-context-protocol,openapi
Requires-Python: >=3.12
Requires-Dist: fastapi>=0.116.0
Requires-Dist: jsonrpc-base>=2.2.0
Requires-Dist: mcp>=1.10.1
Requires-Dist: pydantic>=2.11.7
Requires-Dist: sse-starlette>=2.4.1
Requires-Dist: starlette>=0.46.2
Requires-Dist: typing-extensions>=4.14.1
Requires-Dist: uvicorn>=0.35.0
Provides-Extra: dev
Requires-Dist: coverage>=7.9.2; extra == 'dev'
Requires-Dist: httpx>=0.28.1; extra == 'dev'
Requires-Dist: mypy>=1.16.1; extra == 'dev'
Requires-Dist: pytest-asyncio>=1.0.0; extra == 'dev'
Requires-Dist: pytest-cov>=6.2.1; extra == 'dev'
Requires-Dist: pytest>=8.4.1; extra == 'dev'
Requires-Dist: ruff>=0.12.2; extra == 'dev'
